[{"id":126210680,"repository_id":5533567,"number":"1116","state":"finished","result":null,"started_at":"2016-04-27T20:25:04Z","finished_at":"2016-04-27T20:26:08Z","duration":64,"commit":"445c8908ef968d5a65be87aafe3151a80194a263","branch":"master","message":"Revert \"oops\"\n\nThis reverts commit 3cd3a6595ab2e404586f899ed4c1d3f388555760.","event_type":"push"},{"id":126210012,"repository_id":5533567,"number":"1115","state":"finished","result":null,"started_at":"2016-04-27T20:22:02Z","finished_at":"2016-04-27T20:22:46Z","duration":44,"commit":"3cd3a6595ab2e404586f899ed4c1d3f388555760","branch":"master","message":"oops","event_type":"push"},{"id":126208574,"repository_id":5533567,"number":"1114","state":"finished","result":null,"started_at":"2016-04-27T20:17:21Z","finished_at":"2016-04-27T20:18:11Z","duration":50,"commit":"8cefa21f04cb13c017d879e94ca6412840684b8f","branch":"master","message":"Reformat code","event_type":"push"},{"id":126194882,"repository_id":5533567,"number":"1113","state":"finished","result":0,"started_at":"2016-04-27T19:18:38Z","finished_at":"2016-04-27T19:20:26Z","duration":108,"commit":"dbc6e9e8ad20ecea87464fd087e4e35123fc56bc","branch":"master","message":"Merge pull request #730 from fromgate/reconfig\n\nConfig modification:","event_type":"push"},{"id":126192834,"repository_id":5533567,"number":"1112","state":"finished","result":0,"started_at":"2016-04-27T19:09:12Z","finished_at":"2016-04-27T19:10:23Z","duration":71,"commit":"ffe5be104fd0578b536e7125ffbac4cf73469423","branch":"master","message":"Config modification:\n1. Added ConfigSection as base of Config class.\n2. Added constructor, that allows to create Config instance that not bounded to any file.\n3. Added methods: getSection, getSections, getKeys to improve config usability","event_type":"pull_request"},{"id":126173394,"repository_id":5533567,"number":"1111","state":"finished","result":0,"started_at":"2016-04-27T17:48:35Z","finished_at":"2016-04-27T17:50:13Z","duration":98,"commit":"33e6f9af89b17412f3fce7e6f5ecf69cb0606dda","branch":"master","message":"Merge pull request #729 from boybook/master\n\nReally important fix! Fixed the chunk cache system! Now it works well!!!","event_type":"push"},{"id":126168659,"repository_id":5533567,"number":"1110","state":"finished","result":0,"started_at":"2016-04-27T17:28:38Z","finished_at":"2016-04-27T17:30:04Z","duration":86,"commit":"373e63993e75307af6a31e73b4519097138a4b8b","branch":"master","message":"Really important fix! Fixed the chunk cache system! Now it works well!!!","event_type":"pull_request"},{"id":126112937,"repository_id":5533567,"number":"1109","state":"finished","result":0,"started_at":"2016-04-27T14:02:27Z","finished_at":"2016-04-27T14:03:45Z","duration":78,"commit":"374c1a1b05a6c6007683ffd82742898fec526ce2","branch":"master","message":"Merge pull request #716 from Pub4Game/master\n\nSmall fix","event_type":"push"},{"id":126014818,"repository_id":5533567,"number":"1108","state":"finished","result":0,"started_at":"2016-04-27T04:43:55Z","finished_at":"2016-04-27T04:45:23Z","duration":88,"commit":"db0f2429243b6c86118040b4cd3cb2b31ba421dc","branch":"master","message":"To fix #724","event_type":"push"},{"id":125940519,"repository_id":5533567,"number":"1107","state":"finished","result":0,"started_at":"2016-04-26T20:40:19Z","finished_at":"2016-04-26T20:41:59Z","duration":100,"commit":"6b98959d72472cee464170d42febced386c85a96","branch":"master","message":"Fixed damage when immersed in water","event_type":"push"},{"id":125881060,"repository_id":5533567,"number":"1106","state":"finished","result":0,"started_at":"2016-04-26T16:36:14Z","finished_at":"2016-04-26T16:37:43Z","duration":89,"commit":"120b8a2957aaae0f78f0647d5dd8dc3d06ca5965","branch":"master","message":"Hoe should be tool","event_type":"pull_request"},{"id":125860718,"repository_id":5533567,"number":"1105","state":"finished","result":0,"started_at":"2016-04-26T15:16:40Z","finished_at":"2016-04-26T15:18:44Z","duration":124,"commit":"c7768546ab98ac02ac342426de91c64a16d7463a","branch":"master","message":"Fixed changing armor in creative\n\nTo fix ##711","event_type":"push"},{"id":125837339,"repository_id":5533567,"number":"1104","state":"finished","result":0,"started_at":"2016-04-26T13:52:11Z","finished_at":"2016-04-26T13:53:46Z","duration":95,"commit":"ae87d086813d0bb25295538d3760157096862477","branch":"master","message":"Update README.md","event_type":"push"},{"id":125755687,"repository_id":5533567,"number":"1103","state":"finished","result":0,"started_at":"2016-04-26T06:31:45Z","finished_at":"2016-04-26T06:33:13Z","duration":88,"commit":"b1267dff1d9ae640a25aa5dca40b81fa4d9807b7","branch":"master","message":"Removed duplicate code\n\nThis checking is done in setHealth()","event_type":"push"},{"id":125708610,"repository_id":5533567,"number":"1102","state":"finished","result":0,"started_at":"2016-04-25T23:13:49Z","finished_at":"2016-04-25T23:15:09Z","duration":80,"commit":"34f6f2d31c78123b8b1e0d3ae13a50ed821cc8f9","branch":"master","message":"Merge pull request #714 from Pub4Game/patch-3\n\nTo fix #709","event_type":"push"},{"id":125585518,"repository_id":5533567,"number":"1101","state":"finished","result":0,"started_at":"2016-04-25T14:53:07Z","finished_at":"2016-04-25T14:54:39Z","duration":92,"commit":"aad9320492579f42d405ff782bab498f248581d5","branch":"master","message":"To fix #709","event_type":"pull_request"},{"id":125521852,"repository_id":5533567,"number":"1100","state":"finished","result":0,"started_at":"2016-04-25T09:45:35Z","finished_at":"2016-04-25T09:46:54Z","duration":79,"commit":"7da5c1baea36409c6b45d20b0e6fde004a925aeb","branch":"master","message":"Merge pull request #712 from Creeperface01/patch-7\n\nfix getOnlinePlayers()","event_type":"push"},{"id":125521790,"repository_id":5533567,"number":"1099","state":"finished","result":null,"started_at":"2016-04-25T09:45:08Z","finished_at":"2016-04-25T09:45:27Z","duration":19,"commit":"01939e7a462d37d353db1ec4650bbd8943ffd9e7","branch":"master","message":"fix getOnlinePlayers()","event_type":"pull_request"},{"id":125521510,"repository_id":5533567,"number":"1098","state":"finished","result":0,"started_at":"2016-04-25T09:43:40Z","finished_at":"2016-04-25T09:45:14Z","duration":94,"commit":"256730355963b19fd5a0531f1cad4e29be7c5049","branch":"master","message":"Merge pull request #705 from Creeperface01/patch-5\n\nRevert","event_type":"push"},{"id":125521360,"repository_id":5533567,"number":"1097","state":"finished","result":0,"started_at":"2016-04-25T09:42:52Z","finished_at":"2016-04-25T09:44:17Z","duration":85,"commit":"881fa398616888269821c563b04f36f8cc5d6c8c","branch":"master","message":"Merge pull request #713 from Creeperface01/interact_fix\n\nInteract fix","event_type":"push"},{"id":125413247,"repository_id":5533567,"number":"1096","state":"finished","result":0,"started_at":"2016-04-24T18:32:12Z","finished_at":"2016-04-24T18:33:35Z","duration":83,"commit":"be4f7d00a9b421259bbf9c56df067040c2b69833","branch":"master","message":"fix interact handling in spectator mode","event_type":"pull_request"},{"id":125405866,"repository_id":5533567,"number":"1095","state":"finished","result":0,"started_at":"2016-04-24T17:38:37Z","finished_at":"2016-04-24T17:39:59Z","duration":82,"commit":"025889c503ec2fb479583953d3449d8e49d24970","branch":"master","message":"fix getOnlinePlayers()","event_type":"pull_request"},{"id":125343385,"repository_id":5533567,"number":"1094","state":"finished","result":0,"started_at":"2016-04-24T08:58:26Z","finished_at":"2016-04-24T08:59:54Z","duration":88,"commit":"9c4d7fcb92ec55f23b0d1da09dd49b77cecf51f1","branch":"master","message":"Merge pull request #710 from boybook/master\n\nFixed the NullPointerException when getPlayer(name) in Server class.","event_type":"push"},{"id":125342795,"repository_id":5533567,"number":"1093","state":"finished","result":0,"started_at":"2016-04-24T08:49:46Z","finished_at":"2016-04-24T08:51:26Z","duration":100,"commit":"cfa468c088c37421e02e2a7e040526d5922ac249","branch":"master","message":"Fixed the NullPointerException when getPlayer(name) in Server class.","event_type":"pull_request"},{"id":125203816,"repository_id":5533567,"number":"1092","state":"finished","result":0,"started_at":"2016-04-23T10:47:08Z","finished_at":"2016-04-23T10:48:41Z","duration":93,"commit":"a5b80c6d398b44399ff23ae52ea5f655f3d46081","branch":"master","message":"Merge pull request #10 from Creeperface01/patch-6\n\nUpdate EnchantInventory.java","event_type":"pull_request"}]