[{"id":86826618,"repository_id":1580913,"number":"822","state":"finished","result":null,"started_at":"2015-10-22T13:23:34Z","finished_at":"2015-10-22T13:25:56Z","duration":404,"commit":"95188b299e36e07307945a191387ddfbc71f8559","branch":"master","message":"Refactored transformations to contain the logic in a more object-oriented manner and refactored tests accordingly. Added javadoc.","event_type":"push"},{"id":86817364,"repository_id":1580913,"number":"821","state":"finished","result":null,"started_at":"2015-10-22T12:26:29Z","finished_at":"2015-10-22T12:28:36Z","duration":393,"commit":"5fc3d49a9dbef076a1595133cd8c1e03a5f37f86","branch":"master","message":"Refactored logic further to chain transformations by a compound object rather than by applying a list.","event_type":"push"},{"id":86811780,"repository_id":1580913,"number":"820","state":"finished","result":0,"started_at":"2015-10-22T11:48:17Z","finished_at":"2015-10-22T11:52:44Z","duration":860,"commit":"ebc94dba45a2d68705e9aa0a0decccf2f72c8e0a","branch":"master","message":"Replaced checks for a empty or non-empty size on collections with explicit calls to \"isEmpty()\".","event_type":"push"},{"id":86796135,"repository_id":1580913,"number":"819","state":"finished","result":0,"started_at":"2015-10-22T09:48:01Z","finished_at":"2015-10-22T09:53:20Z","duration":1007,"commit":"92a71bdb9fc61c2fa31142c3db8164daccf7711c","branch":"master","message":"Renamed class visitor chain to compound to apply general naming convention. Added missing javadoc.","event_type":"push"},{"id":86795217,"repository_id":1580913,"number":"818","state":"finished","result":0,"started_at":"2015-10-22T09:42:52Z","finished_at":"2015-10-22T09:48:08Z","duration":955,"commit":"1f83455fed38263f4cbbb3161c59bfda8a37eeaa","branch":"master","message":"Refactored class visitor wrapper to apply an internal combination rather than an explicit chaining.","event_type":"push"},{"id":86727288,"repository_id":1580913,"number":"817","state":"finished","result":0,"started_at":"2015-10-21T22:34:59Z","finished_at":"2015-10-21T22:41:19Z","duration":942,"commit":"0c995250a5311ed6a47aeecd27c06e96f01502f7","branch":"master","message":"Removed unnessecary assertion.","event_type":"push"},{"id":86727234,"repository_id":1580913,"number":"816","state":"finished","result":0,"started_at":"2015-10-21T22:34:24Z","finished_at":"2015-10-21T22:40:33Z","duration":945,"commit":"2cffa90c59e02825e64234c85dec606f3146b5c1","branch":"master","message":"Added explanation on retransformation.","event_type":"push"},{"id":86720101,"repository_id":1580913,"number":"815","state":"finished","result":0,"started_at":"2015-10-21T21:49:20Z","finished_at":"2015-10-21T21:54:51Z","duration":933,"commit":"83a33d23ce449ea6b7f255fe7934cb4806484f15","branch":"master","message":"Added possibility to skip the method implementation when parsing a class file for a type pool to improve performance. Extended parsing needs to be enabled in order to map debugging information to parameter names.","event_type":"push"},{"id":86175134,"repository_id":1580913,"number":"814","state":"finished","result":0,"started_at":"2015-10-19T12:30:48Z","finished_at":"2015-10-19T12:36:23Z","duration":1082,"commit":"ea83f5c0df14d315279b9eaaac65b95017d49e10","branch":"master","message":"Merge pull request #75 from rgoldberg/FixSkipDefaultsIsRelevant\n\nFix net.bytebuddy.implementation.attribute.AnnotationAppender.ValueFilter.SkipDefaults#sRelevant(...)","event_type":"push"},{"id":86173873,"repository_id":1580913,"number":"813","state":"finished","result":0,"started_at":"2015-10-19T12:24:00Z","finished_at":"2015-10-19T12:30:18Z","duration":962,"commit":"5236c204beec40eb7d7d37fee262714d6c166765","branch":"master","message":"Fixed net.bytebuddy.implementation.attribute.AnnotationAppender.ValueFilter.SkipDefaults#sRelevant(...)","event_type":"pull_request"},{"id":86170541,"repository_id":1580913,"number":"812","state":"finished","result":0,"started_at":"2015-10-19T12:06:12Z","finished_at":"2015-10-19T12:13:06Z","duration":1097,"commit":"4a029f76223cd849357ae62ef035df2f228d3913","branch":"master","message":"inverted SkipDefaults expected test results","event_type":"pull_request"},{"id":86168962,"repository_id":1580913,"number":"811","state":"finished","result":1,"started_at":"2015-10-19T11:54:26Z","finished_at":"2015-10-19T11:56:39Z","duration":421,"commit":"6981d33f672b08ccf17b73312196e0d1cfa911d4","branch":"master","message":"checkstyle ! work; checkstyle !!work","event_type":"pull_request"},{"id":86163074,"repository_id":1580913,"number":"810","state":"finished","result":null,"started_at":"2015-10-19T11:08:21Z","finished_at":"2015-10-19T11:10:10Z","duration":355,"commit":"ce604e12b038bc528957f5727413de3e7d7a9aa6","branch":"master","message":"Fix net.bytebuddy.implementation.attribute.AnnotationAppender.ValueFilter.SkipDefaults#sRelevant(...)","event_type":"pull_request"},{"id":85619059,"repository_id":1580913,"number":"809","state":"finished","result":0,"started_at":"2015-10-15T21:18:04Z","finished_at":"2015-10-15T21:23:50Z","duration":884,"commit":"a89035975cbc734be58c4908ab3ad8b786f39d5f","branch":"master","message":"Changed AgentBuilder API to not longer refer to changes of an agent as \"rebase\" as this is now configurable.","event_type":"push"},{"id":85583339,"repository_id":1580913,"number":"808","state":"finished","result":0,"started_at":"2015-10-15T18:06:54Z","finished_at":"2015-10-15T18:12:07Z","duration":920,"commit":"7ed1fb5a096f9f722a41cfbd4e52712213d3c6f0","branch":"master","message":"Updated release notes.","event_type":"push"},{"id":85580743,"repository_id":1580913,"number":"807","state":"finished","result":0,"started_at":"2015-10-15T17:51:51Z","finished_at":"2015-10-15T18:00:45Z","duration":997,"commit":"7641609e6c5b63b140079147aaf63d54a41fa5a6","branch":"master","message":"[maven-release-plugin] prepare for next development iteration","event_type":"push"},{"id":85580735,"repository_id":1580913,"number":"806","state":"finished","result":0,"started_at":"2015-10-15T17:51:43Z","finished_at":"2015-10-15T17:58:36Z","duration":1090,"commit":"35447cd754c2f66944aa6a797cdba1bd5373248c","branch":"master","message":"[maven-release-plugin] prepare release byte-buddy-0.7-rc5","event_type":"push"},{"id":85517958,"repository_id":1580913,"number":"805","state":"finished","result":0,"started_at":"2015-10-15T12:22:04Z","finished_at":"2015-10-15T12:29:02Z","duration":1031,"commit":"0d022b18da2fb337e093017efc9a813c2eb69f0f","branch":"master","message":"Updated release notes.","event_type":"push"},{"id":85512635,"repository_id":1580913,"number":"804","state":"finished","result":0,"started_at":"2015-10-15T11:44:24Z","finished_at":"2015-10-15T11:49:12Z","duration":946,"commit":"81c565bd979a827050126a9327bd7bc4ffcd11d0","branch":"master","message":"Added support for retaining type initializers and specifying redefinition for agent builders. This allows for using type redefinition effectively where it is not allowed to add fields or methods.","event_type":"push"},{"id":85496605,"repository_id":1580913,"number":"803","state":"finished","result":0,"started_at":"2015-10-15T09:43:55Z","finished_at":"2015-10-15T09:49:51Z","duration":1015,"commit":"858a5041aa56490778a3449e19ffaff0d4e43360","branch":"master","message":"Fixed another overvalidation for pre Java-8 interfaces.","event_type":"push"},{"id":85487615,"repository_id":1580913,"number":"802","state":"finished","result":0,"started_at":"2015-10-15T08:42:00Z","finished_at":"2015-10-15T08:47:59Z","duration":1009,"commit":"13ad6426b2cdb058969d709fdcdba5c875b44dc3","branch":"master","message":"Merge pull request #73 from PascalSchumacher/fix_typos\n\nFixed several typos in the release notes.","event_type":"push"},{"id":85487105,"repository_id":1580913,"number":"801","state":"finished","result":0,"started_at":"2015-10-15T08:38:39Z","finished_at":"2015-10-15T08:44:08Z","duration":996,"commit":"b8d7fc59e77848573cdfcc2b5e62ba8a5bd1dc93","branch":"master","message":"fixed some typos","event_type":"pull_request"},{"id":85486025,"repository_id":1580913,"number":"800","state":"finished","result":0,"started_at":"2015-10-15T08:31:55Z","finished_at":"2015-10-15T08:38:27Z","duration":1107,"commit":"23266da61674acf3919dc14eedfeb55cb89908e2","branch":"master","message":"Added current state to release notes.","event_type":"push"},{"id":85485609,"repository_id":1580913,"number":"799","state":"finished","result":0,"started_at":"2015-10-15T08:28:24Z","finished_at":"2015-10-15T08:33:21Z","duration":1021,"commit":"c48d7b48992282a7aab9c685b051307be3b3602c","branch":"master","message":"Minimal clean-up of the POM file.","event_type":"push"},{"id":85436457,"repository_id":1580913,"number":"798","state":"finished","result":0,"started_at":"2015-10-14T23:13:26Z","finished_at":"2015-10-14T23:18:57Z","duration":875,"commit":"04e4a52b2bf709039a7d15afa52ea2022eaacfc7","branch":"master","message":"Modified generic signature that is written by method descriptions to not include generic types if no exception type is generic.","event_type":"push"}]