[{"id":79817606,"repository_id":457050,"number":"344","state":"finished","result":1,"started_at":"2015-09-11T09:48:04Z","finished_at":"2015-09-11T09:52:27Z","duration":263,"commit":"cc8feca78ccfe4165ba5fc181ba1c958c669ca3d","branch":"master","message":"Put process into background when starting openesb standalone in linux.","event_type":"pull_request"},{"id":79817578,"repository_id":457050,"number":"343","state":"finished","result":1,"started_at":"2015-09-11T09:47:59Z","finished_at":"2015-09-11T09:52:26Z","duration":267,"commit":"390eb3fdfd0b517c41c3e1a67dd84a1ecde40507","branch":"enable-more-engines","message":"Put process into background when starting openesb standalone in linux.","event_type":"push"},{"id":79816623,"repository_id":457050,"number":"342","state":"finished","result":null,"started_at":"2015-09-11T09:41:05Z","finished_at":"2015-09-11T09:54:11Z","duration":786,"commit":"349612b0ac62c573aa9abba089be3bc69bba7239","branch":"master","message":"Always use full path to execute a script.","event_type":"pull_request"},{"id":79816611,"repository_id":457050,"number":"341","state":"finished","result":null,"started_at":"2015-09-11T09:41:03Z","finished_at":"2015-09-11T09:45:10Z","duration":247,"commit":"fa44ca29c1073c3076860d74484b5d362c684117","branch":"enable-more-engines","message":"Always use full path to execute a script.","event_type":"push"},{"id":79816283,"repository_id":457050,"number":"340","state":"finished","result":1,"started_at":"2015-09-11T09:38:11Z","finished_at":"2015-09-11T09:42:32Z","duration":261,"commit":"3e31ea4da383258577e9476abcc4dd97e47ca8c5","branch":"master","message":"More details on the wait tasks in the log.","event_type":"pull_request"},{"id":79816281,"repository_id":457050,"number":"339","state":"finished","result":1,"started_at":"2015-09-11T09:38:04Z","finished_at":"2015-09-11T09:42:23Z","duration":259,"commit":"00131178e2cef3628604a664539dcc129896543c","branch":"enable-more-engines","message":"More details on the wait tasks in the log.","event_type":"push"},{"id":79815722,"repository_id":457050,"number":"338","state":"finished","result":1,"started_at":"2015-09-11T09:32:45Z","finished_at":"2015-09-11T09:37:40Z","duration":295,"commit":"3da22a42f75217b9da87ee590d63e0afe0729119","branch":"enable-more-engines","message":"Fix wso2 on windows shutdown script.","event_type":"push"},{"id":79815716,"repository_id":457050,"number":"337","state":"finished","result":1,"started_at":"2015-09-11T09:32:40Z","finished_at":"2015-09-11T09:37:16Z","duration":276,"commit":"a4b47dd5c8b3b2e22f281e9724002509a04c084f","branch":"master","message":"Fix wso2 on windows shutdown script.","event_type":"pull_request"},{"id":79813888,"repository_id":457050,"number":"336","state":"finished","result":1,"started_at":"2015-09-11T09:24:36Z","finished_at":"2015-09-11T09:28:30Z","duration":234,"commit":"d52ccb87c2a1b37e6d9cb1a6682df94ce1eff500","branch":"master","message":"Only wso2 212","event_type":"pull_request"},{"id":79813885,"repository_id":457050,"number":"335","state":"finished","result":1,"started_at":"2015-09-11T09:24:36Z","finished_at":"2015-09-11T09:28:45Z","duration":249,"commit":"3b1d3d54a6bb62656fbcf4d60ce4073a0b128373","branch":"enable-more-engines","message":"Only wso2 212","event_type":"push"},{"id":79813437,"repository_id":457050,"number":"334","state":"finished","result":1,"started_at":"2015-09-11T09:20:40Z","finished_at":"2015-09-11T09:24:48Z","duration":248,"commit":"1d688a2b28406fdc4e523dd6366f0368d43ffed0","branch":"master","message":"Fix wso2 linux startup/shutdown scripts.","event_type":"pull_request"},{"id":79813425,"repository_id":457050,"number":"333","state":"finished","result":1,"started_at":"2015-09-11T09:20:27Z","finished_at":"2015-09-11T09:24:20Z","duration":233,"commit":"90d8214e5dbcf54da32d085f4dc469c4d8fc6615","branch":"enable-more-engines","message":"Fix wso2 linux startup/shutdown scripts.","event_type":"push"},{"id":79809845,"repository_id":457050,"number":"332","state":"finished","result":null,"started_at":"2015-09-11T09:00:57Z","finished_at":"2015-09-11T09:20:18Z","duration":1161,"commit":"09d571bd9e6fca66997321730202f4bae4f29d53","branch":"enable-more-engines","message":"Start wso2 in the background.","event_type":"push"},{"id":79809838,"repository_id":457050,"number":"331","state":"finished","result":null,"started_at":"2015-09-11T09:00:56Z","finished_at":"2015-09-11T09:24:27Z","duration":1411,"commit":"20eb6b26d967c89b2b610660708786dde1b00f5f","branch":"master","message":"Start wso2 in the background.","event_type":"pull_request"},{"id":79808928,"repository_id":457050,"number":"330","state":"finished","result":null,"started_at":"2015-09-11T08:52:30Z","finished_at":"2015-09-11T09:17:05Z","duration":1475,"commit":"82c2aea95e34996b1a9cda52dacd1a0663c17864","branch":"master","message":"Add openesb standalone to the engines to be tested.","event_type":"pull_request"},{"id":79808926,"repository_id":457050,"number":"329","state":"finished","result":null,"started_at":"2015-09-11T08:52:27Z","finished_at":"2015-09-11T08:59:49Z","duration":442,"commit":"1d5431b3eb265511d185509666e85f52cfb529ad","branch":"enable-more-engines","message":"Add openesb standalone to the engines to be tested.","event_type":"push"},{"id":79807670,"repository_id":457050,"number":"328","state":"finished","result":null,"started_at":"2015-09-11T08:54:24Z","finished_at":"2015-09-11T09:17:25Z","duration":1381,"commit":"35e2a9059cbe7f2b95fa29225febbd3767f4cf62","branch":"master","message":"As example processes may interfere, check whether a betsy process is already registered.","event_type":"pull_request"},{"id":79807666,"repository_id":457050,"number":"327","state":"finished","result":null,"started_at":"2015-09-11T08:39:40Z","finished_at":"2015-09-11T08:59:45Z","duration":1205,"commit":"6d2a6543afd647b2e285c067a8063f35c5fcb385","branch":"enable-more-engines","message":"As example processes may interfere, check whether a betsy process is already registered.","event_type":"push"},{"id":79805004,"repository_id":457050,"number":"326","state":"finished","result":1,"started_at":"2015-09-11T08:18:32Z","finished_at":"2015-09-11T08:34:02Z","duration":930,"commit":"9cf71b61d97c72f6e4f97baefd7aadca618ea8cd","branch":"master","message":"Enable test for wso2","event_type":"pull_request"},{"id":79805002,"repository_id":457050,"number":"325","state":"finished","result":1,"started_at":"2015-09-11T08:18:32Z","finished_at":"2015-09-11T08:32:54Z","duration":862,"commit":"a56336fb2dd668adcbc060d3d80878965f39f2ad","branch":"enable-more-engines","message":"Enable test for wso2","event_type":"push"},{"id":79803062,"repository_id":457050,"number":"324","state":"finished","result":0,"started_at":"2015-09-11T08:02:49Z","finished_at":"2015-09-11T08:17:05Z","duration":856,"commit":"cffe1fa4e68365cf3eec1095842fd805ef93f524","branch":"master","message":"Use correct group for invoke sync test.","event_type":"pull_request"},{"id":79745484,"repository_id":457050,"number":"323","state":"finished","result":0,"started_at":"2015-09-10T21:31:40Z","finished_at":"2015-09-10T21:46:03Z","duration":863,"commit":"6c9ddbddded8a6696b87d05cc298eedffc237a2d","branch":"enable-more-engines","message":"Use correct group for invoke sync test.","event_type":"push"},{"id":79727853,"repository_id":457050,"number":"322","state":"finished","result":1,"started_at":"2015-09-10T20:00:41Z","finished_at":"2015-09-10T20:14:07Z","duration":806,"commit":"ebee342b77691e8041e83510a2d61c0f01c9dae1","branch":"enable-more-engines","message":"Add an invoke-sync test.","event_type":"push"},{"id":79724066,"repository_id":457050,"number":"321","state":"finished","result":0,"started_at":"2015-09-10T19:39:47Z","finished_at":"2015-09-10T19:54:21Z","duration":874,"commit":"ca0de2f93952e81197b9485c5fe36ee98de73b7e","branch":"enable-more-engines","message":"The result of Configuration.getJava7Home always returns a valid directory or an exception.","event_type":"push"},{"id":79723717,"repository_id":457050,"number":"320","state":"finished","result":0,"started_at":"2015-09-10T19:37:25Z","finished_at":"2015-09-10T19:51:29Z","duration":844,"commit":"ea2ce6bed7ed856b7432e38e792e7ee88f1edab4","branch":"enable-more-engines","message":"One Java7 should suffice for camunda.","event_type":"push"}]